example_package_chenwenjun/__init__.py
example_package_chenwenjun/analyzer.py
example_package_chenwenjun/hello.py
example_package_chenwenjun/logAnalyzer.cp310-win_amd64.pyd
example_package_chenwenjun-0.0.7.dist-info/METADATA
example_package_chenwenjun-0.0.7.dist-info/WHEEL
example_package_chenwenjun-0.0.7.dist-info/top_level.txt
example_package_chenwenjun-0.0.7.dist-info/RECORD
